{
    "key": "group_674453fd4e1a2",
    "title": "Dropdown item",
    "fields": [
        {
            "key": "field_67458911990b7",
            "label": "Dropdown item",
            "name": "",
            "aria-label": "",
            "type": "accordion",
            "instructions": "",
            "required": 0,
            "conditional_logic": 0,
            "wrapper": {
                "width": "",
                "class": "",
                "id": ""
            },
            "open": 0,
            "multi_expand": 0,
            "endpoint": 0
        },
        {
            "key": "field_674453fd30989",
            "label": "Dropdown titel",
            "name": "dropdown_titel",
            "aria-label": "",
            "type": "text",
            "instructions": "",
            "required": 0,
            "conditional_logic": 0,
            "wrapper": {
                "width": "",
                "class": "",
                "id": ""
            },
            "default_value": "",
            "maxlength": "",
            "allow_in_bindings": 0,
            "placeholder": "",
            "prepend": "",
            "append": ""
        },
        {
            "key": "field_674454513098a",
            "label": "Dropdown items",
            "name": "dropdown_items",
            "aria-label": "",
            "type": "repeater",
            "instructions": "",
            "required": 0,
            "conditional_logic": 0,
            "wrapper": {
                "width": "",
                "class": "",
                "id": ""
            },
            "layout": "block",
            "pagination": 0,
            "min": 0,
            "max": 0,
            "collapsed": "field_6744548b3098b",
            "button_label": "Nieuwe dropdown item",
            "rows_per_page": 20,
            "sub_fields": [
                {
                    "key": "field_6744548b3098b",
                    "label": "Titel",
                    "name": "dropdown_submenu_titel",
                    "aria-label": "",
                    "type": "text",
                    "instructions": "",
                    "required": 0,
                    "conditional_logic": 0,
                    "wrapper": {
                        "width": "",
                        "class": "",
                        "id": ""
                    },
                    "default_value": "Lorem ipsum",
                    "maxlength": "",
                    "allow_in_bindings": 0,
                    "placeholder": "",
                    "prepend": "",
                    "append": "",
                    "parent_repeater": "field_674454513098a"
                },
                {
                    "key": "field_67445916551ac",
                    "label": "Dropdown submenu",
                    "name": "dropdown_submenu",
                    "aria-label": "",
                    "type": "repeater",
                    "instructions": "",
                    "required": 0,
                    "conditional_logic": 0,
                    "wrapper": {
                        "width": "",
                        "class": "",
                        "id": ""
                    },
                    "layout": "block",
                    "min": 0,
                    "max": 0,
                    "collapsed": "field_67445930551ad",
                    "button_label": "Nieuwe dropdown submenu",
                    "rows_per_page": 20,
                    "sub_fields": [
                        {
                            "key": "field_67445930551ad",
                            "label": "Titel",
                            "name": "submenu_titel",
                            "aria-label": "",
                            "type": "text",
                            "instructions": "",
                            "required": 0,
                            "conditional_logic": 0,
                            "wrapper": {
                                "width": "",
                                "class": "",
                                "id": ""
                            },
                            "default_value": "Lorem ipsum",
                            "maxlength": "",
                            "allow_in_bindings": 0,
                            "placeholder": "",
                            "prepend": "",
                            "append": "",
                            "parent_repeater": "field_67445916551ac"
                        },
                        {
                            "key": "field_67445958551ae",
                            "label": "",
                            "name": "dropdown_submenu_item",
                            "aria-label": "",
                            "type": "repeater",
                            "instructions": "",
                            "required": 0,
                            "conditional_logic": 0,
                            "wrapper": {
                                "width": "",
                                "class": "",
                                "id": ""
                            },
                            "layout": "table",
                            "min": 0,
                            "max": 0,
                            "collapsed": "",
                            "button_label": "Nieuwe link",
                            "rows_per_page": 20,
                            "sub_fields": [
                                {
                                    "key": "field_67445974551af",
                                    "label": "Link",
                                    "name": "dropdown_submenu_item_link",
                                    "aria-label": "",
                                    "type": "link",
                                    "instructions": "",
                                    "required": 0,
                                    "conditional_logic": 0,
                                    "wrapper": {
                                        "width": "",
                                        "class": "",
                                        "id": ""
                                    },
                                    "return_format": "array",
                                    "allow_in_bindings": 0,
                                    "parent_repeater": "field_67445958551ae"
                                }
                            ],
                            "parent_repeater": "field_67445916551ac"
                        }
                    ],
                    "parent_repeater": "field_674454513098a"
                }
            ]
        }
    ],
    "location": [
        [
            {
                "param": "options_page",
                "operator": "==",
                "value": "menu"
            }
        ]
    ],
    "menu_order": 1,
    "position": "normal",
    "style": "seamless",
    "label_placement": "top",
    "instruction_placement": "label",
    "hide_on_screen": "",
    "active": true,
    "description": "",
    "show_in_rest": 0,
    "modified": 1732610581
}
